mcpstack_autoddg-0.0.0.dist-info/METADATA
mcpstack_autoddg-0.0.0.dist-info/WHEEL
mcpstack_autoddg-0.0.0.dist-info/entry_points.txt
mcpstack_autoddg-0.0.0.dist-info/licenses/LICENSE
mcpstack_autoddg/__init__.py
mcpstack_autoddg/cli.py
mcpstack_autoddg/core/__init__.py
mcpstack_autoddg/core/sampling.py
mcpstack_autoddg/core/state.py
mcpstack_autoddg/services/__init__.py
mcpstack_autoddg/services/autoddg_service.py
mcpstack_autoddg/tool.py
mcpstack_autoddg-0.0.0.dist-info/RECORD
