Metadata-Version: 2.4
Name: mcpstack-autoddg
Version: 0.0.0
Summary: MCPStack tool exposing the AutoDDG dataset description workflow
Keywords: mcp,mcpstack,autoddg,dataset,description
Author-Email: Provost Simon <s.g.provost@kent.ac.uk>
License-Expression: MIT
Requires-Python: >=3.10
Requires-Dist: typer>=0.9.0
Requires-Dist: beartype>=0.21.0
Requires-Dist: rich>=13.0.0
Requires-Dist: rich-argparse>=1.4.0
Requires-Dist: rich-pyfiglet>=1.0.0
Requires-Dist: click>=8.1.8
Requires-Dist: mcpstack>=0.0.2
Requires-Dist: pandas>=2.2.0
